jockmkt_sdk/__init__.py
jockmkt_sdk/client.py
jockmkt_sdk/exception.py
jockmkt_sdk/objects.py
jockmkt_sdk/jm_sockets/__init__.py
jockmkt_sdk/jm_sockets/sockets.py
jockmkt_sdk/jm_sockets/sockets_update.py
jockmkt_sdk-0.2.15.dist-info/LICENSE.txt
jockmkt_sdk-0.2.15.dist-info/METADATA
jockmkt_sdk-0.2.15.dist-info/WHEEL
jockmkt_sdk-0.2.15.dist-info/top_level.txt
jockmkt_sdk-0.2.15.dist-info/RECORD
