Metadata-Version: 2.1
Name: jockmkt-sdk
Version: 0.2.15
Summary: A basic package allowing the user to interact with Jock MKTs API
Home-page: https://github.com/nysugfx/jockmkt-sdk
Author: Alex Friedman
Author-email: nysu.gfx@gmail.com
Project-URL: BugTracker, https://github.com/nysugfx/jockmkt-sdk/issues
Classifier: Intended Audience :: Developers
Classifier: Topic :: Software Development :: Libraries :: Python Modules
Classifier: License :: OSI Approved :: MIT License
Classifier: Programming Language :: Python :: 3.7
Classifier: Operating System :: OS Independent
Requires-Python: >=3.7
License-File: LICENSE.txt
Requires-Dist: requests (>=0.27.1)
Requires-Dist: pytest (~=7.1.2)
Requires-Dist: certifi (>=2022.9.24)
Requires-Dist: websockets (>=10.3)
